vhdlproc/__init__.py
vhdlproc/vhdlproc.py
vhdlproc/tests/and.vhdl
vhdlproc/tests/include-to.vhdl
vhdlproc/tests/include.vhdl
vhdlproc/tests/nest.vhdl
vhdlproc/tests/test.vhdl
vhdlproc/tests/version.vhdl
vhdlproc-2.3.dist-info/LICENSE
vhdlproc-2.3.dist-info/METADATA
vhdlproc-2.3.dist-info/WHEEL
vhdlproc-2.3.dist-info/entry_points.txt
vhdlproc-2.3.dist-info/top_level.txt
vhdlproc-2.3.dist-info/RECORD
