Metadata-Version: 2.1
Name: vhdlproc
Version: 2.3
Summary: A simple VHDL preprocessor
Home-page: https://github.com/nobodywasishere/vhdlproc
Author: Margret Riegert
Author-email: margret@eowyn.net
License: GPLv3
Platform: UNKNOWN
Classifier: Programming Language :: Python :: 3
Classifier: Programming Language :: Python :: 3.6
Classifier: Programming Language :: Python :: 3.7
Classifier: Programming Language :: Python :: 3.8
Classifier: Programming Language :: Python :: 3.9
Classifier: License :: OSI Approved :: GNU General Public License v3 (GPLv3)
Classifier: Operating System :: OS Independent
License-File: LICENSE
